cli_tweet/__init__.py
cli_tweet/cli.py
cli_tweet/config.py
cli_tweet-1.0.1.dist-info/METADATA
cli_tweet-1.0.1.dist-info/WHEEL
cli_tweet-1.0.1.dist-info/entry_points.txt
cli_tweet-1.0.1.dist-info/licenses/LICENSE
cli_tweet-1.0.1.dist-info/RECORD
