Metadata-Version: 2.4
Name: cli-tweet
Version: 1.0.1
Summary: A small CLI tool to send tweets from your terminal.
Author-email: Yizhen Zheng <cab226023@gmail.com>
License: MIT
License-File: LICENSE
Keywords: cli,tweepy,tweet,twitter
Requires-Python: >=3.10
Requires-Dist: python-dotenv>=1.0.0
Requires-Dist: tweepy>=4.0.0
